{
  "animateLoading": true,
  "borderRadius": "{{appsmith.theme.borderRadius.appBorderRadius}}",
  "bottomRow": 4,
  "boxShadow": "0 0.7em 1.5em -0.5em hsla(249, 62%, 51%, 0.745)",
  "buttonColor": "linear-gradient(\n    90deg,\n    rgba(8, 54, 208, 1) 0%,\n    rgba(12, 116, 254, 1)100%\n)",
  "buttonVariant": "PRIMARY",
  "dynamicBindingPathList": [
    {
      "key": "borderRadius"
    }
  ],
  "dynamicPropertyPathList": [
    {
      "key": "boxShadow"
    },
    {
      "key": "buttonColor"
    }
  ],
  "dynamicTriggerPathList": [
    {
      "key": "onClick"
    }
  ],
  "iconName": "sim-card",
  "isDisabled": false,
  "isLoading": false,
  "isVisible": true,
  "key": "l9am2nf2g1",
  "leftColumn": 59,
  "minWidth": 50,
  "mobileBottomRow": 4,
  "mobileLeftColumn": 59,
  "mobileRightColumn": 63,
  "mobileTopRow": 0,
  "needsErrorInfo": false,
  "onClick": "{{showModal(ORDER_PAYMENT.name);}}",
  "parentColumnSpace": 15.84375,
  "parentId": "jnvzgq6qff",
  "parentRowSpace": 10,
  "renderMode": "CANVAS",
  "responsiveBehavior": "hug",
  "rightColumn": 63,
  "topRow": 0,
  "type": "ICON_BUTTON_WIDGET",
  "version": 1,
  "widgetId": "gzn72ybies",
  "widgetName": "IconButton3"
}