{
  "gitSyncId": "695b4d7d5ddb3153cdfc5984_acdcfe9a-404c-4056-a29a-241d90d2a64a",
  "id": "ASSESSMENT_APPLICANTS_JSObject1.count",
  "pluginId": "js-plugin",
  "pluginType": "JS",
  "unpublishedAction": {
    "actionConfiguration": {
      "encodeParamsToggle": true,
      "jsArguments": [],
      "paginationType": "NONE",
      "timeoutInMillisecond": 10000
    },
    "collectionId": "ASSESSMENT_APPLICANTS_JSObject1",
    "confirmBeforeExecute": false,
    "datasource": {
      "isAutoGenerated": false,
      "name": "UNUSED_DATASOURCE",
      "pluginId": "js-plugin"
    },
    "dynamicBindingPathList": [
      {
        "key": "body"
      }
    ],
    "fullyQualifiedName": "JSObject1.count",
    "name": "count",
    "pageId": "ASSESSMENT_APPLICANTS",
    "runBehaviour": "MANUAL",
    "userSetOnLoad": false
  }
}